{
  "12854832" : [ {
    "date" : "2020-03-17",
    "whenEmpty" : "2020-03-17 13:31:41",
    "whenFew" : "2020-03-17 13:22:29",
    "stock_at" : "2020/03/16 11:49:00",
    "whenSome" : "2020-03-17 12:47:26",
    "whenPlenty" : "2020-03-17 12:02:22",
    "whenBreak" : ""
  } ],
  "11882832" : [ {
    "date" : "2020-03-17",
    "whenEmpty" : "2020-03-17 19:51:59",
    "whenFew" : "2020-03-17 19:32:26",
    "stock_at" : "2020/03/16 17:39:00",
    "whenSome" : "2020-03-17 19:07:04",
    "whenPlenty" : "2020-03-17 18:01:59",
    "whenBreak" : "2020-03-17 17:22:05"
  } ],
  "36831832" : [ {
    "date" : "2020-03-17",
    "whenEmpty" : "2020-03-17 12:36:21",
    "whenFew" : "2020-03-17 12:12:07",
    "stock_at" : "2020/03/16 11:21:00",
    "whenSome" : "2020-03-17 11:42:23",
    "whenPlenty" : "2020-03-17 11:11:42",
    "whenBreak" : ""
  } ],
  "5058301832" : [ {
    "date" : "2020-03-17",
    "whenEmpty" : "2020-03-17 10:41:46",
    "whenFew" : "2020-03-17 10:22:04",
    "stock_at" : "2020/03/16 09:51:00",
    "whenSome" : "2020-03-17 10:06:39",
    "whenPlenty" : "",
    "whenBreak" : ""
  } ],
  "12825832" : [ {
    "date" : "2020-03-17",
    "whenEmpty" : "2020-03-17 14:51:32",
    "whenFew" : "2020-03-17 14:42:09",
    "stock_at" : "2020/03/16 13:51:00",
    "whenSome" : "2020-03-17 14:27:27",
    "whenPlenty" : "2020-03-17 14:11:23",
    "whenBreak" : "2020-03-17 12:56:25"
  } ],
  "37849832" : [ {
    "date" : "2020-03-17",
    "whenEmpty" : "",
    "whenFew" : "2020-03-17 08:57:00",
    "stock_at" : "2020/03/16 11:12:00",
    "whenSome" : "2020-03-17 18:02:02",
    "whenPlenty" : "2020-03-17 11:31:36",
    "whenBreak" : ""
  } ],
  "38833832" : [ {
    "date" : "2020-03-17",
    "whenEmpty" : "2020-03-17 18:06:32",
    "whenFew" : "2020-03-17 16:36:33",
    "stock_at" : "2020/03/16 11:53:00",
    "whenSome" : "2020-03-17 14:11:20",
    "whenPlenty" : "2020-03-17 12:47:18",
    "whenBreak" : ""
  } ],
  "12848832" : [ {
    "date" : "2020-03-17",
    "whenEmpty" : "2020-03-17 13:47:13",
    "whenFew" : "2020-03-17 13:27:04",
    "stock_at" : "2020/03/16 12:49:00",
    "whenSome" : "2020-03-17 13:16:42",
    "whenPlenty" : "2020-03-17 13:02:18",
    "whenBreak" : "2020-03-17 13:42:38"
  } ],
  "39805832" : [ {
    "date" : "2020-03-17",
    "whenEmpty" : "2020-03-17 20:21:09",
    "whenFew" : "2020-03-17 20:17:13",
    "stock_at" : "2020/03/16 17:52:00",
    "whenSome" : "2020-03-17 18:26:16",
    "whenPlenty" : "2020-03-17 17:57:25",
    "whenBreak" : "2020-03-17 16:21:52"
  } ],
  "41806832" : [ {
    "date" : "2020-03-17",
    "whenEmpty" : "2020-03-17 15:22:03",
    "whenFew" : "2020-03-17 14:56:50",
    "stock_at" : "2020/03/16 13:46:00",
    "whenSome" : "2020-03-17 14:17:10",
    "whenPlenty" : "2020-03-17 13:51:53",
    "whenBreak" : ""
  } ],
  "21822832" : [ {
    "date" : "2020-03-17",
    "whenEmpty" : "2020-03-17 17:27:18",
    "whenFew" : "2020-03-17 16:41:38",
    "stock_at" : "2020/03/16 12:35:00",
    "whenSome" : "2020-03-17 17:16:57",
    "whenPlenty" : "2020-03-17 16:46:22",
    "whenBreak" : "2020-03-17 09:07:25"
  } ],
  "41841832" : [ {
    "date" : "2020-03-17",
    "whenEmpty" : "2020-03-17 18:21:35",
    "whenFew" : "2020-03-17 18:01:57",
    "stock_at" : "2020/03/16 17:21:00",
    "whenSome" : "2020-03-17 17:47:33",
    "whenPlenty" : "2020-03-17 17:27:10",
    "whenBreak" : ""
  } ],
  "31843832" : [ {
    "date" : "2020-03-17",
    "whenEmpty" : "2020-03-17 12:07:27",
    "whenFew" : "2020-03-17 11:56:34",
    "stock_at" : "2020/03/16 09:00:00",
    "whenSome" : "2020-03-17 09:58:38",
    "whenPlenty" : "",
    "whenBreak" : ""
  } ],
  "35801832" : [ {
    "date" : "2020-03-17",
    "whenEmpty" : "",
    "whenFew" : "2020-03-17 17:07:16",
    "stock_at" : "2020/03/16 13:44:00",
    "whenSome" : "2020-03-17 16:36:38",
    "whenPlenty" : "2020-03-17 13:02:18",
    "whenBreak" : "2020-03-17 18:12:25"
  } ],
  "36819832" : [ {
    "date" : "2020-03-17",
    "whenEmpty" : "2020-03-17 10:57:36",
    "whenFew" : "2020-03-17 10:51:35",
    "stock_at" : "2020/03/16 10:11:00",
    "whenSome" : "2020-03-17 10:36:59",
    "whenPlenty" : "2020-03-17 09:58:40",
    "whenBreak" : ""
  } ],
  "38810832" : [ {
    "date" : "2020-03-17",
    "whenEmpty" : "2020-03-17 17:31:14",
    "whenFew" : "2020-03-17 17:27:21",
    "stock_at" : "2020/03/16 16:50:00",
    "whenSome" : "2020-03-17 17:17:00",
    "whenPlenty" : "2020-03-17 16:41:40",
    "whenBreak" : ""
  } ],
  "32815832" : [ {
    "date" : "2020-03-17",
    "whenEmpty" : "",
    "whenFew" : "2020-03-17 18:32:48",
    "stock_at" : "2020/03/16 08:42:00",
    "whenSome" : "2020-03-17 13:31:41",
    "whenPlenty" : "2020-03-17 09:07:25",
    "whenBreak" : ""
  } ],
  "5138205832" : [ {
    "date" : "2020-03-17",
    "whenEmpty" : "2020-03-17 14:17:07",
    "whenFew" : "",
    "stock_at" : "2020/03/16 14:00:00",
    "whenSome" : "2020-03-17 14:06:47",
    "whenPlenty" : "2020-03-17 09:16:25",
    "whenBreak" : ""
  } ],
  "35818832" : [ {
    "date" : "2020-03-17",
    "whenEmpty" : "2020-03-17 12:32:31",
    "whenFew" : "2020-03-17 12:12:07",
    "stock_at" : "2020/03/16 09:22:00",
    "whenSome" : "2020-03-17 11:22:02",
    "whenPlenty" : "2020-03-17 10:06:39",
    "whenBreak" : ""
  } ],
  "31895832" : [ {
    "date" : "2020-03-17",
    "whenEmpty" : "2020-03-17 09:27:22",
    "whenFew" : "2020-03-17 09:16:22",
    "stock_at" : "2020/03/16 08:35:00",
    "whenSome" : "2020-03-17 09:01:30",
    "whenPlenty" : "2020-03-17 08:36:17",
    "whenBreak" : ""
  } ],
  "31837832" : [ {
    "date" : "2020-03-17",
    "whenEmpty" : "2020-03-17 10:12:22",
    "whenFew" : "",
    "stock_at" : "2020/03/16 08:29:00",
    "whenSome" : "",
    "whenPlenty" : "",
    "whenBreak" : "2020-03-17 09:32:28"
  } ],
  "21839832" : [ {
    "date" : "2020-03-17",
    "whenEmpty" : "2020-03-17 10:51:36",
    "whenFew" : "2020-03-17 10:41:50",
    "stock_at" : "2020/03/16 09:53:00",
    "whenSome" : "2020-03-17 10:27:23",
    "whenPlenty" : "2020-03-17 09:48:52",
    "whenBreak" : ""
  } ],
  "11818832" : [ {
    "date" : "2020-03-17",
    "whenEmpty" : "",
    "whenFew" : "2020-03-17 18:02:01",
    "stock_at" : "2020/03/16 15:15:00",
    "whenSome" : "2020-03-17 16:21:49",
    "whenPlenty" : "2020-03-17 15:06:29",
    "whenBreak" : ""
  } ],
  "41835832" : [ {
    "date" : "2020-03-17",
    "whenEmpty" : "2020-03-17 18:21:38",
    "whenFew" : "2020-03-17 18:01:59",
    "stock_at" : "2020/03/16 16:58:00",
    "whenSome" : "2020-03-17 17:46:21",
    "whenPlenty" : "2020-03-17 17:16:55",
    "whenBreak" : ""
  } ]
}