{
  "37850661" : [ {
    "date" : "2020-03-17",
    "whenEmpty" : "2020-03-17 16:12:43",
    "whenFew" : "2020-03-17 14:21:43",
    "stock_at" : "2020/03/16 09:59:00",
    "whenSome" : "2020-03-17 12:17:54",
    "whenPlenty" : "2020-03-17 10:03:13",
    "whenBreak" : ""
  } ],
  "35810661" : [ {
    "date" : "2020-03-17",
    "whenEmpty" : "2020-03-17 00:35:14",
    "whenFew" : "",
    "stock_at" : "2020/03/16 13:48:00",
    "whenSome" : "2020-03-17 17:42:12",
    "whenPlenty" : "2020-03-17 14:02:11",
    "whenBreak" : ""
  } ],
  "41818661" : [ {
    "date" : "2020-03-17",
    "whenEmpty" : "2020-03-17 12:07:33",
    "whenFew" : "2020-03-17 11:47:26",
    "stock_at" : "2020/03/16 10:32:00",
    "whenSome" : "",
    "whenPlenty" : "",
    "whenBreak" : "2020-03-17 10:27:23"
  } ],
  "41847661" : [ {
    "date" : "2020-03-17",
    "whenEmpty" : "2020-03-17 19:16:46",
    "whenFew" : "",
    "stock_at" : "2020/03/16 10:16:00",
    "whenSome" : "",
    "whenPlenty" : "",
    "whenBreak" : "2020-03-17 17:42:13"
  } ],
  "37806661" : [ {
    "date" : "2020-03-17",
    "whenEmpty" : "2020-03-17 15:55:42",
    "whenFew" : "2020-03-17 14:46:44",
    "stock_at" : "2020/03/16 11:17:00",
    "whenSome" : "2020-03-17 12:36:21",
    "whenPlenty" : "2020-03-17 10:06:39",
    "whenBreak" : "2020-03-17 00:35:12"
  } ],
  "38839661" : [ {
    "date" : "2020-03-17",
    "whenEmpty" : "2020-03-17 00:35:18",
    "whenFew" : "",
    "stock_at" : "2020/03/16 09:39:00",
    "whenSome" : "2020-03-17 16:56:23",
    "whenPlenty" : "2020-03-17 15:51:55",
    "whenBreak" : "2020-03-17 17:27:21"
  } ],
  "37844661" : [ {
    "date" : "2020-03-17",
    "whenEmpty" : "2020-03-17 00:35:10",
    "whenFew" : "",
    "stock_at" : "2020/03/10 11:01:00",
    "whenSome" : "",
    "whenPlenty" : "",
    "whenBreak" : ""
  } ],
  "11859661" : [ {
    "date" : "2020-03-17",
    "whenEmpty" : "2020-03-17 16:21:44",
    "whenFew" : "2020-03-17 16:12:37",
    "stock_at" : "2020/03/16 14:50:00",
    "whenSome" : "2020-03-17 16:07:26",
    "whenPlenty" : "2020-03-17 14:52:47",
    "whenBreak" : ""
  } ],
  "37829661" : [ {
    "date" : "2020-03-17",
    "whenEmpty" : "2020-03-17 15:11:33",
    "whenFew" : "2020-03-17 14:17:06",
    "stock_at" : "2020/03/16 09:31:00",
    "whenSome" : "2020-03-17 12:07:25",
    "whenPlenty" : "2020-03-17 09:42:26",
    "whenBreak" : ""
  } ],
  "31878661" : [ {
    "date" : "2020-03-17",
    "whenEmpty" : "2020-03-17 15:47:17",
    "whenFew" : "2020-03-17 14:27:27",
    "stock_at" : "2020/03/16 09:17:00",
    "whenSome" : "2020-03-17 14:02:11",
    "whenPlenty" : "2020-03-17 13:47:13",
    "whenBreak" : ""
  } ],
  "5138205661" : [ {
    "date" : "2020-03-17",
    "whenEmpty" : "2020-03-17 00:35:16",
    "whenFew" : "2020-03-17 15:01:53",
    "stock_at" : "2020/03/16 13:48:00",
    "whenSome" : "2020-03-17 14:02:13",
    "whenPlenty" : "2020-03-17 13:56:28",
    "whenBreak" : ""
  } ],
  "12808661" : [ {
    "date" : "2020-03-17",
    "whenEmpty" : "2020-03-17 17:02:22",
    "whenFew" : "2020-03-17 16:57:30",
    "stock_at" : "2020/03/16 09:06:00",
    "whenSome" : "2020-03-17 15:51:49",
    "whenPlenty" : "",
    "whenBreak" : ""
  } ],
  "36805661" : [ {
    "date" : "2020-03-17",
    "whenEmpty" : "2020-03-17 10:22:09",
    "whenFew" : "2020-03-17 10:12:26",
    "stock_at" : "2020/03/16 09:22:00",
    "whenSome" : "2020-03-17 09:42:28",
    "whenPlenty" : "2020-03-17 09:12:36",
    "whenBreak" : ""
  } ],
  "34832661" : [ {
    "date" : "2020-03-17",
    "whenEmpty" : "2020-03-17 15:32:24",
    "whenFew" : "2020-03-17 15:36:59",
    "stock_at" : "2020/03/16 12:56:00",
    "whenSome" : "2020-03-17 14:06:49",
    "whenPlenty" : "",
    "whenBreak" : "2020-03-17 00:35:16"
  } ],
  "1228203661" : [ {
    "date" : "2020-03-17",
    "whenEmpty" : "2020-03-17 14:27:27",
    "whenFew" : "2020-03-17 14:11:23",
    "stock_at" : "2020/03/16 13:28:00",
    "whenSome" : "2020-03-17 14:06:47",
    "whenPlenty" : "2020-03-17 13:16:42",
    "whenBreak" : "2020-03-17 14:21:42"
  } ],
  "37838661" : [ {
    "date" : "2020-03-17",
    "whenEmpty" : "",
    "whenFew" : "2020-03-17 09:36:26",
    "stock_at" : "2020/03/16 12:57:00",
    "whenSome" : "2020-03-17 16:16:32",
    "whenPlenty" : "2020-03-17 10:31:55",
    "whenBreak" : "2020-03-17 17:46:18"
  } ],
  "31881661" : [ {
    "date" : "2020-03-17",
    "whenEmpty" : "2020-03-17 13:22:27",
    "whenFew" : "2020-03-17 13:16:42",
    "stock_at" : "2020/03/16 12:40:00",
    "whenSome" : "2020-03-17 13:11:55",
    "whenPlenty" : "2020-03-17 12:42:12",
    "whenBreak" : ""
  } ],
  "12857661" : [ {
    "date" : "2020-03-17",
    "whenEmpty" : "2020-03-17 20:56:30",
    "whenFew" : "2020-03-17 20:46:45",
    "stock_at" : "2020/03/16 12:19:00",
    "whenSome" : "2020-03-17 20:01:39",
    "whenPlenty" : "2020-03-17 11:51:59",
    "whenBreak" : "2020-03-17 14:36:23"
  } ],
  "34841661" : [ {
    "date" : "2020-03-17",
    "whenEmpty" : "2020-03-17 17:47:34",
    "whenFew" : "2020-03-17 17:42:11",
    "stock_at" : "2020/03/16 16:53:00",
    "whenSome" : "2020-03-17 17:22:02",
    "whenPlenty" : "2020-03-17 17:02:24",
    "whenBreak" : ""
  } ],
  "31898661" : [ {
    "date" : "2020-03-17",
    "whenEmpty" : "2020-03-17 10:41:44",
    "whenFew" : "2020-03-17 10:36:51",
    "stock_at" : "2020/03/16 10:08:00",
    "whenSome" : "2020-03-17 10:27:12",
    "whenPlenty" : "2020-03-17 10:12:22",
    "whenBreak" : ""
  } ],
  "41821661" : [ {
    "date" : "2020-03-17",
    "whenEmpty" : "2020-03-17 12:21:23",
    "whenFew" : "2020-03-17 12:17:57",
    "stock_at" : "2020/03/16 08:24:00",
    "whenSome" : "2020-03-17 08:57:00",
    "whenPlenty" : "2020-03-17 08:31:46",
    "whenBreak" : ""
  } ],
  "11804661" : [ {
    "date" : "2020-03-17",
    "whenEmpty" : "2020-03-17 17:12:12",
    "whenFew" : "2020-03-17 16:12:37",
    "stock_at" : "2020/03/16 13:46:00",
    "whenSome" : "2020-03-17 14:52:47",
    "whenPlenty" : "2020-03-17 13:56:25",
    "whenBreak" : ""
  } ],
  "31869661" : [ {
    "date" : "2020-03-17",
    "whenEmpty" : "2020-03-17 20:12:13",
    "whenFew" : "2020-03-17 18:32:48",
    "stock_at" : "2020/03/16 13:59:00",
    "whenSome" : "2020-03-17 18:21:39",
    "whenPlenty" : "2020-03-17 14:31:38",
    "whenBreak" : "2020-03-17 18:17:03"
  } ],
  "41844661" : [ {
    "date" : "2020-03-17",
    "whenEmpty" : "2020-03-17 14:36:26",
    "whenFew" : "2020-03-17 14:26:20",
    "stock_at" : "2020/03/16 13:30:00",
    "whenSome" : "2020-03-17 14:02:14",
    "whenPlenty" : "2020-03-17 13:31:42",
    "whenBreak" : ""
  } ],
  "11856661" : [ {
    "date" : "2020-03-17",
    "whenEmpty" : "2020-03-17 13:16:41",
    "whenFew" : "2020-03-17 12:51:11",
    "stock_at" : "2020/03/16 09:44:00",
    "whenSome" : "2020-03-17 12:12:07",
    "whenPlenty" : "2020-03-17 09:31:13",
    "whenBreak" : ""
  } ],
  "31846661" : [ {
    "date" : "2020-03-17",
    "whenEmpty" : "2020-03-17 16:21:52",
    "whenFew" : "2020-03-17 16:16:40",
    "stock_at" : "2020/03/16 09:39:00",
    "whenSome" : "2020-03-17 11:22:06",
    "whenPlenty" : "2020-03-17 10:27:23",
    "whenBreak" : ""
  } ],
  "12866661" : [ {
    "date" : "2020-03-17",
    "whenEmpty" : "2020-03-17 17:46:24",
    "whenFew" : "2020-03-17 17:22:08",
    "stock_at" : "2020/03/16 16:46:00",
    "whenSome" : "2020-03-17 17:16:57",
    "whenPlenty" : "2020-03-17 16:56:20",
    "whenBreak" : "2020-03-17 17:42:13"
  } ],
  "4118200661" : [ {
    "date" : "2020-03-17",
    "whenEmpty" : "",
    "whenFew" : "",
    "stock_at" : "2020/03/16 12:49:00",
    "whenSome" : "2020-03-17 14:06:46",
    "whenPlenty" : "2020-03-17 12:21:19",
    "whenBreak" : ""
  } ],
  "12820661" : [ {
    "date" : "2020-03-17",
    "whenEmpty" : "2020-03-17 16:26:56",
    "whenFew" : "2020-03-17 16:07:26",
    "stock_at" : "2020/03/16 14:24:00",
    "whenSome" : "2020-03-17 15:26:35",
    "whenPlenty" : "2020-03-17 14:31:33",
    "whenBreak" : ""
  } ],
  "11879661" : [ {
    "date" : "2020-03-17",
    "whenEmpty" : "2020-03-17 18:01:59",
    "whenFew" : "2020-03-17 17:36:23",
    "stock_at" : "2020/03/16 16:46:00",
    "whenSome" : "2020-03-17 17:27:16",
    "whenPlenty" : "2020-03-17 16:36:38",
    "whenBreak" : ""
  } ],
  "38836661" : [ {
    "date" : "2020-03-17",
    "whenEmpty" : "2020-03-17 18:41:55",
    "whenFew" : "2020-03-17 18:32:44",
    "stock_at" : "2020/03/16 17:30:00",
    "whenSome" : "2020-03-17 18:16:58",
    "whenPlenty" : "2020-03-17 17:42:09",
    "whenBreak" : ""
  } ],
  "38807661" : [ {
    "date" : "2020-03-17",
    "whenEmpty" : "2020-03-17 18:36:15",
    "whenFew" : "2020-03-17 16:02:17",
    "stock_at" : "2020/03/16 12:42:00",
    "whenSome" : "2020-03-17 14:27:29",
    "whenPlenty" : "2020-03-17 12:31:19",
    "whenBreak" : ""
  } ],
  "21840661" : [ {
    "date" : "2020-03-17",
    "whenEmpty" : "2020-03-17 16:41:34",
    "whenFew" : "2020-03-17 16:12:35",
    "stock_at" : "2020/03/16 14:53:00",
    "whenSome" : "2020-03-17 15:32:20",
    "whenPlenty" : "2020-03-17 15:01:49",
    "whenBreak" : "2020-03-17 14:56:39"
  } ],
  "11813661" : [ {
    "date" : "2020-03-17",
    "whenEmpty" : "2020-03-17 18:26:15",
    "whenFew" : "2020-03-17 17:42:13",
    "stock_at" : "2020/03/16 15:49:00",
    "whenSome" : "2020-03-17 17:22:08",
    "whenPlenty" : "2020-03-17 15:55:47",
    "whenBreak" : "2020-03-17 20:51:56"
  } ],
  "11836661" : [ {
    "date" : "2020-03-17",
    "whenEmpty" : "2020-03-17 14:42:09",
    "whenFew" : "2020-03-17 14:37:33",
    "stock_at" : "2020/03/16 13:52:00",
    "whenSome" : "2020-03-17 14:27:27",
    "whenPlenty" : "2020-03-17 13:47:13",
    "whenBreak" : ""
  } ],
  "21834661" : [ {
    "date" : "2020-03-17",
    "whenEmpty" : "",
    "whenFew" : "",
    "stock_at" : "2020/03/16 07:59:00",
    "whenSome" : "",
    "whenPlenty" : "2020-03-17 15:51:52",
    "whenBreak" : "2020-03-17 17:57:19"
  } ],
  "32810661" : [ {
    "date" : "2020-03-17",
    "whenEmpty" : "2020-03-17 00:35:12",
    "whenFew" : "2020-03-17 18:06:34",
    "stock_at" : "2020/03/16 08:28:00",
    "whenSome" : "2020-03-17 14:42:07",
    "whenPlenty" : "2020-03-17 09:01:30",
    "whenBreak" : "2020-03-17 19:16:43"
  } ],
  "41838661" : [ {
    "date" : "2020-03-17",
    "whenEmpty" : "2020-03-17 10:22:01",
    "whenFew" : "2020-03-17 10:12:22",
    "stock_at" : "2020/03/16 08:57:00",
    "whenSome" : "2020-03-17 09:42:24",
    "whenPlenty" : "2020-03-17 09:12:28",
    "whenBreak" : ""
  } ],
  "21819661" : [ {
    "date" : "2020-03-17",
    "whenEmpty" : "2020-03-17 15:32:20",
    "whenFew" : "",
    "stock_at" : "2020/03/16 12:47:00",
    "whenSome" : "",
    "whenPlenty" : "",
    "whenBreak" : "2020-03-17 14:42:06"
  } ],
  "36834661" : [ {
    "date" : "2020-03-17",
    "whenEmpty" : "2020-03-17 11:01:27",
    "whenFew" : "2020-03-17 10:51:36",
    "stock_at" : "2020/03/16 10:39:00",
    "whenSome" : "2020-03-17 10:37:02",
    "whenPlenty" : "2020-03-17 10:12:28",
    "whenBreak" : "2020-03-17 10:57:39"
  } ],
  "34806661" : [ {
    "date" : "2020-03-17",
    "whenEmpty" : "2020-03-17 11:56:31",
    "whenFew" : "2020-03-17 11:51:56",
    "stock_at" : "2020/03/16 10:31:00",
    "whenSome" : "2020-03-17 11:01:20",
    "whenPlenty" : "2020-03-17 10:27:12",
    "whenBreak" : ""
  } ],
  "5098303661" : [ {
    "date" : "2020-03-17",
    "whenEmpty" : "2020-03-17 15:11:31",
    "whenFew" : "2020-03-17 10:36:51",
    "stock_at" : "2020/03/16 08:49:00",
    "whenSome" : "2020-03-17 08:56:54",
    "whenPlenty" : "2020-03-17 08:52:19",
    "whenBreak" : ""
  } ],
  "31817661" : [ {
    "date" : "2020-03-17",
    "whenEmpty" : "2020-03-17 16:12:37",
    "whenFew" : "2020-03-17 15:55:42",
    "stock_at" : "2020/03/16 09:22:00",
    "whenSome" : "2020-03-17 15:01:50",
    "whenPlenty" : "2020-03-17 13:47:12",
    "whenBreak" : "2020-03-17 10:51:32"
  } ],
  "31832661" : [ {
    "date" : "2020-03-17",
    "whenEmpty" : "2020-03-17 18:26:13",
    "whenFew" : "2020-03-17 18:06:36",
    "stock_at" : "2020/03/16 12:54:00",
    "whenSome" : "2020-03-17 13:37:31",
    "whenPlenty" : "2020-03-17 12:56:25",
    "whenBreak" : ""
  } ],
  "5058301661" : [ {
    "date" : "2020-03-17",
    "whenEmpty" : "",
    "whenFew" : "2020-03-17 09:48:50",
    "stock_at" : "2020/03/16 10:18:00",
    "whenSome" : "2020-03-17 11:26:40",
    "whenPlenty" : "2020-03-17 10:06:42",
    "whenBreak" : ""
  } ],
  "21811661" : [ {
    "date" : "2020-03-17",
    "whenEmpty" : "2020-03-17 19:12:09",
    "whenFew" : "2020-03-17 18:36:14",
    "stock_at" : "2020/03/16 10:44:00",
    "whenSome" : "",
    "whenPlenty" : "2020-03-17 13:06:55",
    "whenBreak" : "2020-03-17 17:12:13"
  } ],
  "38822661" : [ {
    "date" : "2020-03-17",
    "whenEmpty" : "",
    "whenFew" : "",
    "stock_at" : "2020/03/16 15:28:00",
    "whenSome" : "",
    "whenPlenty" : "2020-03-17 00:35:14",
    "whenBreak" : ""
  } ],
  "12837661" : [ {
    "date" : "2020-03-17",
    "whenEmpty" : "2020-03-17 12:56:23",
    "whenFew" : "2020-03-17 12:21:19",
    "stock_at" : "2020/03/16 08:55:00",
    "whenSome" : "2020-03-17 12:12:07",
    "whenPlenty" : "2020-03-17 11:17:27",
    "whenBreak" : "2020-03-17 11:42:23"
  } ]
}